odoo10_addon_account_invoice_line_sequence-10.0.1.0.0-py2.7-nspkg.pth
odoo/addons/account_invoice_line_sequence/README.rst
odoo/addons/account_invoice_line_sequence/__init__.py
odoo/addons/account_invoice_line_sequence/__manifest__.py
odoo/addons/account_invoice_line_sequence/init_hooks.py
odoo/addons/account_invoice_line_sequence/models/__init__.py
odoo/addons/account_invoice_line_sequence/models/invoice.py
odoo/addons/account_invoice_line_sequence/views/account_invoice_view.xml
odoo/addons/account_invoice_line_sequence/views/report_invoice.xml
odoo10_addon_account_invoice_line_sequence-10.0.1.0.0.dist-info/DESCRIPTION.rst
odoo10_addon_account_invoice_line_sequence-10.0.1.0.0.dist-info/METADATA
odoo10_addon_account_invoice_line_sequence-10.0.1.0.0.dist-info/RECORD
odoo10_addon_account_invoice_line_sequence-10.0.1.0.0.dist-info/WHEEL
odoo10_addon_account_invoice_line_sequence-10.0.1.0.0.dist-info/metadata.json
odoo10_addon_account_invoice_line_sequence-10.0.1.0.0.dist-info/namespace_packages.txt
odoo10_addon_account_invoice_line_sequence-10.0.1.0.0.dist-info/top_level.txt
